{
  "white" : {

    "video_file" : "video/20180507_led_calibration_2.AVI",
    "image_file" : "image/20180507_led_calibration_2/access_white.png",
    "fps" : 30.0,
    "loc" : [342, 691],
    "h" : 11,
    "w" : 11,
    "start" : 1555,
    "end" : 3517
  },
  "blue" : {

    "video_file" : "video/20180507_led_calibration_2.AVI",
    "image_file" : "image/20180507_led_calibration_2/access_blue.png",
    "fps" : 30.0,
    "loc" : [337, 691],
    "h" : 11,
    "w" : 11,
    "start" : 3521,
    "end" : 5483,
    "color_num" : 2
  },
  "green" : {

    "video_file" : "video/20180507_led_calibration_2.AVI",
    "image_file" : "image/20180507_led_calibration_2/access_green.png",
    "fps" : 30.0,
    "loc" : [337, 683],
    "h" : 11,
    "w" : 11,
    "start" : 5489,
    "end" : 7449,
    "color_num" : 1
  },
  "red" : {

    "video_file" : "video/20180507_led_calibration_2.AVI",
    "image_file" : "image/20180507_led_calibration_2/access_red.png",
    "fps" : 30.0,
    "loc" : [342, 683],
    "h" : 11,
    "w" : 11,
    "start" : 7452,
    "end" : 9415,
    "color_num" : 0
  }
}
